qiniuManager/__init__.py
qiniuManager/crypto.py
qiniuManager/http.py
qiniuManager/manager.py
qiniuManager/progress.py
qiniuManager/run.py
qiniuManager/utils.py
qiniuManager-1.4.11.dist-info/DESCRIPTION.rst
qiniuManager-1.4.11.dist-info/METADATA
qiniuManager-1.4.11.dist-info/RECORD
qiniuManager-1.4.11.dist-info/WHEEL
qiniuManager-1.4.11.dist-info/entry_points.txt
qiniuManager-1.4.11.dist-info/metadata.json
qiniuManager-1.4.11.dist-info/top_level.txt
