Metadata-Version: 1.1
Name: qiniuManager
Version: 1.4.11
Summary: 终端管理七牛云空间
Home-page: https://github.com/hellflame/qiniu_manager
Author: hellflame
Author-email: hellflamedly@gmail.com
License: MIT
Keywords: qiniu,qiniu manager
Platform: UNIX like
Classifier: Development Status :: 5 - Production/Stable
Classifier: Intended Audience :: Developers
Classifier: License :: OSI Approved :: MIT License
Classifier: Environment :: Console
Classifier: Operating System :: MacOS
Classifier: Operating System :: MacOS :: MacOS X
Classifier: Operating System :: POSIX
Classifier: Operating System :: POSIX :: Linux
Classifier: Programming Language :: Python :: 2.7
